library/__init__.py
library/admin.py
library/apps.py
library/models.py
library/tests.py
library/views.py
library/migrations/0001_initial.py
library/migrations/__init__.py
rupam_library-0.1.dist-info/METADATA
rupam_library-0.1.dist-info/WHEEL
rupam_library-0.1.dist-info/top_level.txt
rupam_library-0.1.dist-info/RECORD
