Metadata-Version: 2.1
Name: rupam-library
Version: 0.1
Summary: Description of your Django app
Author: Your Name
Author-email: your@email.com
License: MIT License
Classifier: Environment :: Web Environment
Classifier: Framework :: Django
Classifier: Programming Language :: Python :: 3.10
Classifier: License :: OSI Approved :: MIT License
Classifier: Operating System :: OS Independent
Requires-Dist: Django >=3.0
